linesegmentintersections/AVLTree.py
linesegmentintersections/BentleyOttmann.py
linesegmentintersections/Endpoint.py
linesegmentintersections/Event.py
linesegmentintersections/Intersection.py
linesegmentintersections/Node.py
linesegmentintersections/PriorityQueue.py
linesegmentintersections/Segment.py
linesegmentintersections/__init__.py
linesegmentintersections/button.py
linesegmentintersections/helper.py
linesegmentintersections/line.py
linesegmentintersections/sweepline.py
linesegmentintersections/sweepline_interface.py
test/__init__.py
test/test_BentleyOttmann.py
test/test_avl_tree.py
test/test_intersections.py
test/test_priority_queue.py
test/test_sweepline_interface.py
line_segment_intersections-0.1.3.dist-info/LICENSE
line_segment_intersections-0.1.3.dist-info/METADATA
line_segment_intersections-0.1.3.dist-info/WHEEL
line_segment_intersections-0.1.3.dist-info/top_level.txt
line_segment_intersections-0.1.3.dist-info/RECORD
