Metadata-Version: 2.1
Name: line-segment-intersections
Version: 0.1.3
Summary: Implementation of Bentley-Ottman algorithm for finding line segment intersections.
Home-page: https://github.com/LiahNikol/line-segment-intersections
Author: Liah Carpenter and Aaron Ott
License: MIT license
Platform: UNKNOWN
Requires-Dist: numpy (>=1.19.0)
